flask_statsd_tagged.py
setup.py
Flask_StatsdTagged.egg-info/PKG-INFO
Flask_StatsdTagged.egg-info/SOURCES.txt
Flask_StatsdTagged.egg-info/dependency_links.txt
Flask_StatsdTagged.egg-info/not-zip-safe
Flask_StatsdTagged.egg-info/requires.txt
Flask_StatsdTagged.egg-info/top_level.txt