Metadata-Version: 1.1
Name: Flask-StatsdTagged
Version: 0.7
Summary: Flask extension for sending statsd data with tags, for use with telegraf statsd plugin
Home-page: https://github.com/forsberg/Flask-Statsd-Tagged/
Author: Erik Forsberg
Author-email: forsberg@efod.se
License: BSD
Platform: any
Classifier: Environment :: Web Environment
Classifier: Intended Audience :: Developers
Classifier: License :: OSI Approved :: BSD License
Classifier: Operating System :: OS Independent
Classifier: Programming Language :: Python
Classifier: Topic :: Internet :: WWW/HTTP :: Dynamic Content
Classifier: Topic :: Software Development :: Libraries :: Python Modules
